ds_workflow/__init__.py
ds_workflow/ds_workflow_creator.py
ds_workflow-0.1.dist-info/LICENSE
ds_workflow-0.1.dist-info/METADATA
ds_workflow-0.1.dist-info/WHEEL
ds_workflow-0.1.dist-info/top_level.txt
ds_workflow-0.1.dist-info/RECORD
