Metadata-Version: 2.1
Name: ds_workflow
Version: 0.1
Summary: Data Science end-to-end Workflow
Author: Victor Uwaje
License: MIT
Platform: UNKNOWN
License-File: LICENSE
